{
    "stations" : {
        "Airport" : [
            "Line 4
        ],
        "South Keys" : [
            "Line 2",
            "Line 4"
        ],
        "Uplands" : [
            "Line 4"
        ]
    },
    "lines" : {
        "Line 4" : {
            "0" : [
                "South Keys",
                "Uplands",
                "Airport
            ],
            "1" : [
                "Airport",
                "Uplands",
                "South Keys"
            ]
        }
    }
}
